{
    "image_url": "https://i0.wp.com/nontonanimeid.cfd/wp-content/uploads/2023/03/Shingeki-no-Kyojin-The-Final-Season-Kanketsu-hen.jpg?h=240",
    "desc": "Shingeki no Kyojin: The Final Season – Kanketsu-hen menceritakan tentang: Lanjutan dari Shingeki no Kyojin: The Final Season Part 2.",
    "episode_list": [
        {
            "date": "Mar 4, 2023",
            "episode": "Episode 1",
            "watch_url": "https://nontonanimeid.cfd/shingeki-no-kyojin-the-final-season-kanketsu-hen-episode-1/"
        }
    ]
}